earthground/.DS_Store
earthground/__init__.py
earthground/components.py
earthground/footprint_types.py
earthground/schematic.py
earthground/standard_values.py
earthground/utils.py
earthground/exporters/__init__.py
earthground/exporters/kicad.py
earthground/footprints/__init__.py
earthground/footprints/generics.py
earthground/footprints/header.py
earthground/footprints/passives.py
earthground/footprints/qfn.py
earthground/footprints/tssop.py
earthground/library/footprints/__init__.py
earthground/library/footprints/generics.py
earthground/library/footprints/header.py
earthground/library/footprints/passives.py
earthground/library/footprints/qfn.py
earthground/library/footprints/tssop.py
earthground/library/headers/connectors.py
earthground/library/headers/jst.py
earthground/library/integrated_circuits/__init__.py
earthground/library/integrated_circuits/interface_sensor/cypress_mbr3.py
earthground/library/integrated_circuits/io_expanders/tca9535pwr.py
earthground/library/integrated_circuits/motor_drivers/tmc2100.py
earthground/library/misc/testpoints.py
earthground/library/modules/blackpill.py
earthground/library/modules/raspberry_pi_hat.py
earthground/library/protocols/serial.py
earthground/library/voltage_regulators/ap7330.py
earthground-0.1.0.dist-info/WHEEL
earthground-0.1.0.dist-info/METADATA
earthground-0.1.0.dist-info/RECORD
