Metadata-Version: 2.1
Name: earthground
Version: 0.1.0
Summary: A Python Library for Creating Software-Defined Electrical Designs
Author: esophagoose
Classifier: Programming Language :: Python :: 3
Classifier: Operating System :: OS Independent
Requires-Dist: kiutils==1.4.8
Requires-Dist: python-gerber>=0.1.0
Requires-Dist: pytest>=7.4.2
Requires-Dist: pytest>6 ; extra == "test"
Project-URL: Source, https://github.com/esophagoose/earthground
Provides-Extra: test
